importer/__init__.py
importer/import_constants.py
constants_importer-1.0.0.dist-info/METADATA
constants_importer-1.0.0.dist-info/WHEEL
constants_importer-1.0.0.dist-info/top_level.txt
constants_importer-1.0.0.dist-info/RECORD
